us_census_api_extract/__init__.py
us_census_api_extract-0.2.8.dist-info/LICENSE
us_census_api_extract-0.2.8.dist-info/METADATA
us_census_api_extract-0.2.8.dist-info/WHEEL
us_census_api_extract-0.2.8.dist-info/top_level.txt
us_census_api_extract-0.2.8.dist-info/RECORD
