Metadata-Version: 2.1
Name: us-census-api-extract
Version: 0.2.8
Summary: Extract US census data (as a DataFrame) by inputting a list of demographic variables and US state codes.
Home-page: https://github.com/AndoKalrisian/us_census_api_extract
Author: Anders Bergman
Author-email: 
License: MIT License
Platform: UNKNOWN
Classifier: Programming Language :: Python :: 3
Classifier: License :: OSI Approved :: MIT License
Classifier: Operating System :: OS Independent
Requires-Python: >=3.6
Requires-Dist: progress-keeper
Requires-Dist: pandas
Requires-Dist: numpy
